torrt/__init__.py
torrt/base_bot.py
torrt/base_notifier.py
torrt/base_rpc.py
torrt/base_tracker.py
torrt/exceptions.py
torrt/main.py
torrt/toolbox.py
torrt/utils.py
torrt/bots/__init__.py
torrt/bots/telegram_bot.py
torrt/notifiers/__init__.py
torrt/notifiers/mail.py
torrt/notifiers/telegram.py
torrt/rpc/__init__.py
torrt/rpc/deluge.py
torrt/rpc/qbittorrent.py
torrt/rpc/transmission.py
torrt/rpc/utorrent.py
torrt/trackers/__init__.py
torrt/trackers/anidub.py
torrt/trackers/anilibria.py
torrt/trackers/casstudio.py
torrt/trackers/eniahd.py
torrt/trackers/kinozal.py
torrt/trackers/nnmclub.py
torrt/trackers/rutor.py
torrt/trackers/rutracker.py
torrt/trackers/ytsmx.py
torrt-1.0.0.dist-info/AUTHORS
torrt-1.0.0.dist-info/LICENSE
torrt-1.0.0.dist-info/METADATA
torrt-1.0.0.dist-info/WHEEL
torrt-1.0.0.dist-info/entry_points.txt
torrt-1.0.0.dist-info/top_level.txt
torrt-1.0.0.dist-info/RECORD
