Metadata-Version: 2.1
Name: torrt
Version: 1.0.0
Summary: Automates torrent updates for you.
Home-page: https://github.com/idlesign/torrt
Author: Igor `idle sign` Starikov
Author-email: idlesign@yandex.ru
License: BSD 3-Clause License
Platform: UNKNOWN
Classifier: Development Status :: 4 - Beta
Classifier: Operating System :: OS Independent
Classifier: Programming Language :: Python
Classifier: Programming Language :: Python :: 3
Classifier: Programming Language :: Python :: 3.6
Classifier: Programming Language :: Python :: 3.7
Classifier: Programming Language :: Python :: 3.8
Classifier: Programming Language :: Python :: 3.9
Classifier: Programming Language :: Python :: 3.10
Classifier: License :: OSI Approved :: BSD License
Requires-Dist: requests
Requires-Dist: beautifulsoup4
Requires-Dist: torrentool
Requires-Dist: lxml
Provides-Extra: telegram
Requires-Dist: python-telegram-bot (<12.0.0a0,>=11.1.0) ; extra == 'telegram'
